citation_parser/__init__.py
citation_parser/__version__.py
citation_parser/kb_addenda.py
citation_parser/antlr/__init__.py
citation_parser/antlr/cp_lexer.py
citation_parser/antlr/cp_parser.py
citation_parser/antlr/cp_treeparser.py
citation_parser-0.4.1.dist-info/DESCRIPTION.rst
citation_parser-0.4.1.dist-info/METADATA
citation_parser-0.4.1.dist-info/RECORD
citation_parser-0.4.1.dist-info/WHEEL
citation_parser-0.4.1.dist-info/dependency_links.txt
citation_parser-0.4.1.dist-info/metadata.json
citation_parser-0.4.1.dist-info/top_level.txt
