Metadata-Version: 2.0
Name: citation-parser
Version: 0.4.1
Summary: A parser for canonical references.
Home-page: https://github.com/mromanello/CitationParser
Author: Matteo Romanello
Author-email: matteo.romanello@gmail.com
License: GPL v3
Platform: UNKNOWN
Classifier: Intended Audience :: Science/Research
Classifier: Programming Language :: Python :: 2.7
Classifier: Operating System :: POSIX
Requires-Dist: antlr-python-runtime
Requires-Dist: pyCTS
